{
  "code": 200,
  "msg": "",
  "bond": {
    "bond_id": "110077",
    "bond_nm": "洪城转债",
    "market": "sh",
    "btype": "C",
    "price": 185.505,
    "full_price": 185.505,
    "interest": 0,
    "convert_dt": 0,
    "convert_cd_tip": "2021-05-26 开始转股",
    "convert_price_valid": "Y",
    "redeem_flag": "N",
    "redeem_icon": "G",
    "bond_nm_tip": "本次（2024年5月31日至2024年6月21日）不提前赎回，以2025年6月22日为首个交易日重\r\n新计算",
    "increase_rt": "-0.31",
    "curr_iss_amt": "6.685",
    "orig_iss_amt": "18.000",
    "volume": "1876.55",
    "turnover_rt": 1.51,
    "convert_value": 170.97,
    "year_left": "1.860",
    "convert_amt_ratio": 6.1,
    "convert_amt_ratio2": 5.7,
    "ytm_rt": -24.103,
    "ytm_rt_tax": -24.93,
    "sell": [
      {
        "type": "sell5",
        "price": 185.947,
        "amount": 0.186,
        "ytm": -24.232,
        "premium_rt": 8.76
      },
      {
        "type": "sell4",
        "price": 185.8,
        "amount": 0.743,
        "ytm": -24.2,
        "premium_rt": 8.67
      },
      {
        "type": "sell3",
        "price": 185.713,
        "amount": 3.529,
        "ytm": -24.18,
        "premium_rt": 8.62
      },
      {
        "type": "sell2",
        "price": 185.711,
        "amount": 0.371,
        "ytm": -24.18,
        "premium_rt": 8.62
      },
      {
        "type": "sell1",
        "price": 185.71,
        "amount": 0.557,
        "ytm": -24.18,
        "premium_rt": 8.62
      }
    ],
    "buy": [
      {
        "type": "buy1",
        "price": 185.5,
        "amount": 125.398,
        "ytm": -24.133,
        "premium_rt": 8.5
      },
      {
        "type": "buy2",
        "price": 185.16,
        "amount": 5.184,
        "ytm": -24.058,
        "premium_rt": 8.3
      },
      {
        "type": "buy3",
        "price": 185,
        "amount": 1.11,
        "ytm": -24.022,
        "premium_rt": 8.2
      },
      {
        "type": "buy4",
        "price": 184.807,
        "amount": 92.404,
        "ytm": -23.979,
        "premium_rt": 8.09
      },
      {
        "type": "buy5",
        "price": 184.699,
        "amount": 0.185,
        "ytm": -23.955,
        "premium_rt": 8.03
      }
    ],
    "low": 184.251,
    "high": 186.887,
    "open": 186.361,
    "close": 186.077,
    "quote_info": "",
    "suspension_news": ""
  },
  "stock": {
    "stock_id": "600461",
    "stock_nm": "洪城环境",
    "price": 9.13,
    "increase_rt": "-0.54",
    "volume": "7926.56",
    "stdevry": 31.77,
    "change_rate": 0.72,
    "dividend_rate": "4.053",
    "total_value": "117.24",
    "float_value": "109.35",
    "int_debt_rate": 44.46,
    "debt_rate": 58.53,
    "pe": 10.41,
    "pb": 1.296,
    "pb_flag": "N",
    "sell": [
      {
        "type": "sell5",
        "price": 9.18,
        "amount": 61.781
      },
      {
        "type": "sell4",
        "price": 9.17,
        "amount": 35.488
      },
      {
        "type": "sell3",
        "price": 9.16,
        "amount": 8.061
      },
      {
        "type": "sell2",
        "price": 9.15,
        "amount": 4.118
      },
      {
        "type": "sell1",
        "price": 9.14,
        "amount": 1.462
      }
    ],
    "buy": [
      {
        "type": "buy1",
        "price": 9.13,
        "amount": 17.347
      },
      {
        "type": "buy2",
        "price": 9.12,
        "amount": 91.838
      },
      {
        "type": "buy3",
        "price": 9.11,
        "amount": 65.137
      },
      {
        "type": "buy4",
        "price": 9.1,
        "amount": 104.195
      },
      {
        "type": "buy5",
        "price": 9.09,
        "amount": 165.62
      }
    ],
    "low": 9.09,
    "high": 9.21,
    "open": 9.15,
    "close": 9.18,
    "quote_info": ""
  }
}